rpi_thermo_chick/__init__.py
rpi_thermo_chick/api.py
rpi_thermo_chick/index.html
rpi_thermo_chick/influxdb.py
rpi_thermo_chick/relays.py
rpi_thermo_chick/rpi-thermo-chick.service
rpi_thermo_chick/sensors.py
rpi_thermo_chick/service.py
rpi_thermo_chick-1.2.5.dist-info/LICENSE
rpi_thermo_chick-1.2.5.dist-info/METADATA
rpi_thermo_chick-1.2.5.dist-info/WHEEL
rpi_thermo_chick-1.2.5.dist-info/entry_points.txt
rpi_thermo_chick-1.2.5.dist-info/top_level.txt
rpi_thermo_chick-1.2.5.dist-info/RECORD
