Metadata-Version: 2.1
Name: rpi-thermo-chick
Version: 1.2.5
Summary: Raspberry Pi - Thermostat 🔥 for chicken 🐔
Home-page: https://github.com/vrince/rpi-thermo-chick
Author: Thomas Vincent
Author-email: vrince@gmail.com
License: MIT
Platform: UNKNOWN
License-File: LICENSE
Requires-Dist: appdirs (==1.4.4)
Requires-Dist: click (==8.0.3)
Requires-Dist: fastapi (==0.70.0)
Requires-Dist: influxdb-client (==1.33.0)
Requires-Dist: uvicorn[standard] (==0.15.0)
